{
"type": "FeatureCollection",
"name": "Aluminum",
"crs": { "type": "name", "properties": { "name": "urn:ogc:def:crs:OGC:1.3:CRS84" } },
"features": [
{ "type": "Feature", "properties": { "id": 0, "Plant": "MARTIN-MARIETTA ALUMINUM CO. - The Dalles", "EPA": "https:\/\/cumulis.epa.gov\/supercpad\/cursites\/csitinfo.cfm?id=1000424", "Date const": "1958", "Date idled": "1987" }, "geometry": { "type": "Point", "coordinates": [ -121.2071, 45.6247 ] } },
{ "type": "Feature", "properties": { "id": 1, "Plant": "Alcoa - Vancouver Smelter", "EPA": "https:\/\/cumulis.epa.gov\/supercpad\/cursites\/csitinfo.cfm?id=1000597", "Date const": "1940", "Date idled": "1985" }, "geometry": { "type": "Point", "coordinates": [ -122.7339, 45.6497 ] } },
{ "type": "Feature", "properties": { "id": 2, "Plant": "KAISER ALUMINUM - MEAD WORKS", "EPA": "https:\/\/cumulis.epa.gov\/supercpad\/cursites\/csitinfo.cfm?id=1000551", "Date const": "1942", "Date idled": "1978" }, "geometry": { "type": "Point", "coordinates": [ -117.3746, 47.755 ] } },
{ "type": "Feature", "properties": { "id": 3, "Plant": "Anaconda Aluminum - COLUMBIA FALLS REDUCTION PLANT", "EPA": "https:\/\/cumulis.epa.gov\/supercpad\/cursites\/csitinfo.cfm?id=0800392", "Date const": "1955", "Date idled": "2009" }, "geometry": { "type": "Point", "coordinates": [ -114.1347, 48.3931 ] } },
{ "type": "Feature", "properties": { "id": 4, "Plant": "Kaiser Aluminum - Tacoma", "EPA": "https:\/\/fortress.wa.gov\/ecy\/gsp\/Sitepage.aspx?csid=2215", "Date const": "1942", "Date idled": "2000" }, "geometry": { "type": "Point", "coordinates": [ -122.3704, 47.2601 ] } },
{ "type": "Feature", "properties": { "id": 6, "Plant": "Alcoa Intalco Works - Ferndale", "EPA": null, "Date const": "1966", "Date idled": null }, "geometry": { "type": "Point", "coordinates": [ -122.7058, 48.8456 ] } },
{ "type": "Feature", "properties": { "id": 7, "Plant": "Alcoa Wenatchee Works - Wenatchee", "EPA": null, "Date const": null, "Date idled": null }, "geometry": { "type": "Point", "coordinates": [ -120.1256, 47.3559 ] } },
{ "type": "Feature", "properties": { "id": 8, "Plant": "Columbia Gorge Aluminum Smelter -Goldendale", "EPA": "https:\/\/fortress.wa.gov\/ecy\/gsp\/Sitepage.aspx?csid=11797L", "Date const": "1969", "Date idled": "2003" }, "geometry": { "type": "Point", "coordinates": [ -120.6991, 45.7324 ] } },
{ "type": "Feature", "properties": { "id": 5, "Plant": "Reynolds Metals Co - Troutdale", "EPA": "https:\/\/cumulis.epa.gov\/supercpad\/SiteProfiles\/index.cfm?fuseaction=second.Cleanup&id=1000383#bkground", "Date const": "1941", "Date idled": "2000" }, "geometry": { "type": "Point", "coordinates": [ -122.4009, 45.5569 ] } },
{ "type": "Feature", "properties": { "id": 9, "Plant": "Reynolds Metals Aluminum Plant -  Longview", "EPA": "https:\/\/fortress.wa.gov\/ecy\/gsp\/Sitepage.aspx?csid=11796", "Date const": "1941", "Date idled": "2000" }, "geometry": { "type": "Point", "coordinates": [ -122.9998, 46.1414 ] } }
]
}
