{
  "type": "FeatureCollection",
  "crs": {
    "type": "name",
    "properties": {
      "name": "urn:ogc:def:crs:OGC:1.3:CRS84"
    }
  },
  "features": [
    {
      "type": "Feature",
      "properties": {
        "Name": "",
        "Image": "",
        "website": "<strong>The history of humanity is one long sentence. The poet's duty is to contradict it.</strong>",
        "EPA": "",
        "Notes": "René Char"
      },
      "geometry": {
        "type": "Point",
        "coordinates": [
          -34.086,
          40.387
        ]
      }
    }
  ]
}
