{
"type": "FeatureCollection",
"name": "Deconstruction",
"crs": { "type": "name", "properties": { "name": "urn:ogc:def:crs:OGC:1.3:CRS84" } },
"features": [
{ "type": "Feature", "properties": { "id": 1, "icon": "icons/1sm.png", "image": "<img src='images/Deconstruction1.jpg'>" }, "geometry": { "type": "Point", "coordinates": [ -124.041735451305357, 46.384599998437544 ] } },
{ "type": "Feature", "properties": { "id": 2, "icon": "icons/2sm.png", "image": "<img src='images/Deconstruction2.jpg'>" }, "geometry": { "type": "Point", "coordinates": [ -123.986235451305362, 46.369399998437544 ] } },
{ "type": "Feature", "properties": { "id": 3, "icon": "icons/3sm.png", "image": "<img src='images/Deconstruction3.jpg'>" }, "geometry": { "type": "Point", "coordinates": [ -123.962535451305357, 46.330499998437546 ] } },
{ "type": "Feature", "properties": { "id": 4, "icon": "icons/4sm.png", "image": "<img src='images/Deconstruction4.jpg'>" }, "geometry": { "type": "Point", "coordinates": [ -123.985835451305348, 46.290699998437546 ] } },
{ "type": "Feature", "properties": { "id": 5, "icon": "icons/5sm.png", "image": "<img src='images/Deconstruction5.jpg'>" }, "geometry": { "type": "Point", "coordinates": [ -124.041735451305357, 46.275199998437543 ] } },
{ "type": "Feature", "properties": { "id": 6, "icon": "icons/6sm.png", "image": "<img src='images/Deconstruction6.jpg'>" }, "geometry": { "type": "Point", "coordinates": [ -124.097535451305362, 46.290999998437542 ] } },
{ "type": "Feature", "properties": { "id": 7, "icon": "icons/7sm.png", "image": "<img src='images/Deconstruction7.jpg'>" }, "geometry": { "type": "Point", "coordinates": [ -124.121335451305356, 46.329899998437547 ] } },
{ "type": "Feature", "properties": { "id": 8, "icon": "icons/8sm.png", "image": "<img src='images/Deconstruction8.jpg'>" }, "geometry": { "type": "Point", "coordinates": [ -124.098435451305349, 46.368499998437542 ] } }
]
}
