{
"type": "FeatureCollection",
"crs": { "type": "name", "properties": { "name": "urn:ogc:def:crs:OGC:1.3:CRS84" } },

"features": [
{ "type": "Feature", "properties": { "title": "<strong>What caused the fire?</strong>",
"image": "<img src='images/Surface.png'><br>",
"text1": "<em>Map showing land surface temperature from April 26–May 3, 2016. Red areas were hotter than the 2000–2010 average for the same one-week period, blue areas were cooler.</em>",
"text2": "<strong>Wildfire scientist Mike Flanigan answers the crucial question:</strong> <br>\"'This is a result of human-caused climate change. There's a lot of year-to-year variability with area burned, but we have doubled it.'<br>According to research Flannigan published in the journal </em>Climatic Change<em>, for every degree in warming, 15 per cent more precipitation is needed to offset the risk of wildfire from drying fuel.\"</em>",
"text3": "Source <a href='http://phys.org/news/2016-05-fort-mcmurray-blaze-extreme-wildfires.html#jCp'>here</a>" },
"geometry": { "type": "Point", "coordinates": [ -111.3889, 56.753571 ] } }
]
}
